biotop/__init__.py
biotop/misc.py
biotop/peak_picker.py
biotop/preprocess_ecg_detectors.py
biotop/respiration_picker.py
biotop-0.5.3.dist-info/LICENSE.txt
biotop-0.5.3.dist-info/METADATA
biotop-0.5.3.dist-info/WHEEL
biotop-0.5.3.dist-info/entry_points.txt
biotop-0.5.3.dist-info/top_level.txt
biotop-0.5.3.dist-info/RECORD
