Metadata-Version: 2.1
Name: biotop
Version: 0.5.3
Summary: Semi-automated extrema detection in ECG and respiratory signals
Author-email: Floris van Vugt <floris.van.vugt@umontreal.ca>
Maintainer-email: Floris van Vugt <floris.van.vugt@umontreal.ca>
License: Apache License
Project-URL: Homepage, https://github.com/florisvanvugt/biotop
Project-URL: Bug Reports, https://github.com/florisvanvugt/biotop/issues
Project-URL: Source, https://github.com/florisvanvugt/biotop
Keywords: ECG,cardiac,biosignals,peak detection,signal processing,respiration
Requires-Python: >=3.8
License-File: LICENSE.txt
Requires-Dist: neurokit2
Requires-Dist: py-ecg-detectors
Requires-Dist: matplotlib >3.7.0
Requires-Dist: scipy
Requires-Dist: numpy
Requires-Dist: biobabel
Requires-Dist: heartpy
